local_ai_utils_core/__init__.py
local_ai_utils_core/clients.py
local_ai_utils_core/config.py
local_ai_utils_core/core.py
local_ai_utils_core/plugin_manager.py
local_ai_utils_core/ui/__init__.py
local_ai_utils_core/ui/base.py
local_ai_utils_core/ui/external.py
local_ai_utils_core/ui/push_notifications.py
local_ai_utils_core/ui/terminal.py
local_ai_utils_core/ui/ui.py
local_ai_utils_core-0.2.5.dist-info/licenses/LICENSE
local_ai_utils_core-0.2.5.dist-info/METADATA
local_ai_utils_core-0.2.5.dist-info/WHEEL
local_ai_utils_core-0.2.5.dist-info/top_level.txt
local_ai_utils_core-0.2.5.dist-info/RECORD
